.dockerignore
.gitignore
CONTRIBUTORS.rst
Dockerfile
LICENSE
MANIFEST.in
README.rst
requirements-dev.txt
requirements.txt
setup.cfg
setup.py
version.txt
doc/Makefile
doc/environment.yml
doc/make.bat
doc/source/conf.py
doc/source/index.rst
doc/source/_static/style.css
doc/source/_templates/layout.html
doc/source/getting_started/Citations.rst
doc/source/getting_started/Contributing.rst
doc/source/getting_started/Install.rst
doc/source/getting_started/Overview.rst
doc/source/getting_started/Resources.rst
doc/source/user_guide/append_YAPC_ICESat2_ATL03.rst
doc/source/user_guide/classify_photons.rst
doc/source/user_guide/utilities.rst
pyYAPC.egg-info/PKG-INFO
pyYAPC.egg-info/SOURCES.txt
pyYAPC.egg-info/dependency_links.txt
pyYAPC.egg-info/requires.txt
pyYAPC.egg-info/top_level.txt
scripts/append_YAPC_ICESat2_ATL03.py
yapc/__init__.py
yapc/_dist_metrics.pxd
yapc/_dist_metrics.pyx
yapc/classify_photons.py
yapc/utilities.py
yapc/version.py