Metadata-Version: 2.1
Name: pyYAPC
Version: 0.0.0.8
Summary: Python version of the NASA GSFC YAPC ("Yet Another Photon Classifier") Program
Home-page: https://github.com/tsutterley/yapc
Author: Tyler Sutterley
Author-email: tsutterl@uw.edu
License: MIT
Keywords: ICESat-2 laser altimetry,ATLAS,photon classification,kNN filtering
Classifier: Development Status :: 3 - Alpha
Classifier: Intended Audience :: Science/Research
Classifier: Topic :: Scientific/Engineering :: Physics
Classifier: License :: OSI Approved :: MIT License
Classifier: Programming Language :: Python :: 3
Classifier: Programming Language :: Python :: 3.6
Classifier: Programming Language :: Python :: 3.7
Classifier: Programming Language :: Python :: 3.8
License-File: LICENSE
